localPrivacy_martaajonees/__init__.py
localPrivacy_martaajonees/count_mean/__init__.py
localPrivacy_martaajonees/count_mean/cms_client_mean.py
localPrivacy_martaajonees/count_mean/private_cms_client.py
localPrivacy_martaajonees/count_mean/private_cms_server.py
localPrivacy_martaajonees/hadamard_count_mean/__init__.py
localPrivacy_martaajonees/hadamard_count_mean/private_hcms_client.py
localPrivacy_martaajonees/hadamard_count_mean/private_hcms_server.py
localPrivacy_martaajonees/main/__init__.py
localPrivacy_martaajonees/main/general_method.py
localPrivacy_martaajonees/main/individual_method.py
localPrivacy_martaajonees/scripts/__init__.py
localPrivacy_martaajonees/scripts/parameter_fitting.py
localPrivacy_martaajonees/scripts/preprocess.py
localPrivacy_martaajonees/utils/__init__.py
localPrivacy_martaajonees/utils/utils.py
localprivacy_martaajonees-1.0.2.dist-info/METADATA
localprivacy_martaajonees-1.0.2.dist-info/WHEEL
localprivacy_martaajonees-1.0.2.dist-info/licenses/LICENSE
localprivacy_martaajonees-1.0.2.dist-info/RECORD
