Metadata-Version: 2.4
Name: localPrivacy_martaajonees
Version: 1.0.2
Summary: Adaptation of differential privacy algorithms applied to learning analytics.
Project-URL: Homepage, https://github.com/martaajonees/Local_Privacy
Project-URL: Issues, https://github.com/martaajonees/Local_Privacy/issues
Author-email: Marta Jones González <martajon10@gmail.com>
License-Expression: MIT
License-File: LICENSE
Classifier: Operating System :: OS Independent
Classifier: Programming Language :: Python :: 3
Requires-Python: >=3.8
